radCAD_core-0.1.2.dist-info/METADATA
radCAD_core-0.1.2.dist-info/WHEEL
radCAD.cpython-38-darwin.so
radCAD_core-0.1.2.dist-info/RECORD
