Metadata-Version: 2.1
Name: radCAD-core
Version: 0.1.2
Classifier: Programming Language :: Python
Summary: A Rust cadCAD implementation, for dynamical systems modelling & simulation
Keywords: simulation modelling dynamical-systems cad
Home-Page: https://github.com/BenSchZA/radCAD
Author: Benjamin Scholtz
